{
  "generated_at": "2026-06-27T15:45:30.159729",
  "summary": {
    "total_members": 47,
    "matched": 0,
    "unmatched": 47,
    "total_vimeo_videos": 0,
    "taidan_videos": 0
  },
  "matched": [],
  "unmatched": [
    {
      "guest_name": "hiraiさん",
      "search_keys": [
        "hirai"
      ],
      "near_candidates": []
    },
    {
      "guest_name": "真生さん",
      "search_keys": [
        "真生"
      ],
      "near_candidates": []
    },
    {
      "guest_name": "PAYさん",
      "search_keys": [
        "PAY",
        "pay",
        "Pay"
      ],
      "near_candidates": []
    },
    {
      "guest_name": "RYOさん",
      "search_keys": [
        "RYO"
      ],
      "near_candidates": []
    },
    {
      "guest_name": "やーまんさん",
      "search_keys": [
        "ヤーマン",
        "やーまん"
      ],
      "near_candidates": []
    },
    {
      "guest_name": "ろくさん",
      "search_keys": [
        "ろく",
        "ロク"
      ],
      "near_candidates": []
    },
    {
      "guest_name": "ひろきょうさん",
      "search_keys": [
        "ヒロキョウ",
        "ひろきょう"
      ],
      "near_candidates": []
    },
    {
      "guest_name": "松本さん",
      "search_keys": [
        "松本"
      ],
      "near_candidates": []
    },
    {
      "guest_name": "Izuさん",
      "search_keys": [
        "Lzu",
        "luz",
        "Izu",
        "lzu"
      ],
      "near_candidates": []
    },
    {
      "guest_name": "こもさん",
      "search_keys": [
        "こも",
        "コモ"
      ],
      "near_candidates": []
    },
    {
      "guest_name": "てぃーひろさん",
      "search_keys": [
        "てぃーひろ",
        "ティーヒロ"
      ],
      "near_candidates": []
    },
    {
      "guest_name": "りょうすけさん",
      "search_keys": [
        "リョウスケ",
        "りょうすけ"
      ],
      "near_candidates": []
    },
    {
      "guest_name": "さるビールさん",
      "search_keys": [
        "さるびーる",
        "さるビール",
        "サルビール"
      ],
      "near_candidates": []
    },
    {
      "guest_name": "みんてぃあさん",
      "search_keys": [
        "みんてぃあ",
        "ミンティア"
      ],
      "near_candidates": []
    },
    {
      "guest_name": "しおさん",
      "search_keys": [
        "シオ",
        "しお"
      ],
      "near_candidates": []
    },
    {
      "guest_name": "ゆきもるさん",
      "search_keys": [
        "雪森",
        "ユキモル",
        "ゆきもり",
        "ユキモリ",
        "ゆきもる"
      ],
      "near_candidates": []
    },
    {
      "guest_name": "スリマンさん",
      "search_keys": [
        "すりまん",
        "スリマン"
      ],
      "near_candidates": []
    },
    {
      "guest_name": "あさかつさん",
      "search_keys": [
        "アサカツ",
        "あさかつ"
      ],
      "near_candidates": []
    },
    {
      "guest_name": "くますけさん",
      "search_keys": [
        "くまき",
        "クマキ",
        "クマスケ",
        "くますけ"
      ],
      "near_candidates": []
    },
    {
      "guest_name": "アンディさん",
      "search_keys": [
        "アンディ",
        "あんでぃ"
      ],
      "near_candidates": []
    },
    {
      "guest_name": "ロキさん",
      "search_keys": [
        "ろき",
        "ロキ"
      ],
      "near_candidates": []
    },
    {
      "guest_name": "けーさん",
      "search_keys": [
        "ケー",
        "けー"
      ],
      "near_candidates": []
    },
    {
      "guest_name": "さくらさん",
      "search_keys": [
        "さくら",
        "サクラ"
      ],
      "near_candidates": []
    },
    {
      "guest_name": "ゆりかさん",
      "search_keys": [
        "ユリカ",
        "ゆりか"
      ],
      "near_candidates": []
    },
    {
      "guest_name": "コテさん",
      "search_keys": [
        "こてつ",
        "コテ",
        "コテツ",
        "こて"
      ],
      "near_candidates": []
    },
    {
      "guest_name": "kosさん",
      "search_keys": [
        "コスト",
        "こすと",
        "kos"
      ],
      "near_candidates": []
    },
    {
      "guest_name": "メンイチさん",
      "search_keys": [
        "メンイチ",
        "めいじ",
        "めんいち",
        "メイジ"
      ],
      "near_candidates": []
    },
    {
      "guest_name": "さといも・トーマスさん",
      "search_keys": [
        "さといも",
        "とーます",
        "さといも・トーマス",
        "さといも・とーます",
        "サトイモ",
        "トーマス",
        "サトイモ・トーマス"
      ],
      "near_candidates": []
    },
    {
      "guest_name": "ハオさん",
      "search_keys": [
        "はお",
        "羽生",
        "ハオ"
      ],
      "near_candidates": []
    },
    {
      "guest_name": "TMさん",
      "search_keys": [
        "TM"
      ],
      "near_candidates": []
    },
    {
      "guest_name": "バーボンさん",
      "search_keys": [
        "バーボン",
        "ばーぼん"
      ],
      "near_candidates": []
    },
    {
      "guest_name": "ハラさん",
      "search_keys": [
        "ハラ",
        "はら"
      ],
      "near_candidates": []
    },
    {
      "guest_name": "キリマルさん",
      "search_keys": [
        "キリマル",
        "きりまる"
      ],
      "near_candidates": []
    },
    {
      "guest_name": "えりっくさん",
      "search_keys": [
        "エリック",
        "えりっく"
      ],
      "near_candidates": []
    },
    {
      "guest_name": "しゃちぽこさん",
      "search_keys": [
        "シャチポコ",
        "しゃちぽこ"
      ],
      "near_candidates": []
    },
    {
      "guest_name": "ウメさん",
      "search_keys": [
        "うめ",
        "ウメ"
      ],
      "near_candidates": []
    },
    {
      "guest_name": "GENさん",
      "search_keys": [
        "GEN"
      ],
      "near_candidates": []
    },
    {
      "guest_name": "ゼットンさん",
      "search_keys": [
        "ぜっとん",
        "ゼットン"
      ],
      "near_candidates": []
    },
    {
      "guest_name": "ちーさん",
      "search_keys": [
        "ちー",
        "チー"
      ],
      "near_candidates": []
    },
    {
      "guest_name": "ブンさん",
      "search_keys": [
        "ぶん",
        "ブン"
      ],
      "near_candidates": []
    },
    {
      "guest_name": "ふみさん",
      "search_keys": [
        "フミ",
        "ふみ"
      ],
      "near_candidates": []
    },
    {
      "guest_name": "ワンルームマンション",
      "search_keys": [
        "ワンルームマンション",
        "わんるーむまんしょん"
      ],
      "near_candidates": []
    },
    {
      "guest_name": "黄金の羽",
      "search_keys": [
        "黄金ノ羽",
        "黄金の羽"
      ],
      "near_candidates": []
    },
    {
      "guest_name": "金持ちがやらないこと / 会社員が取らない方がいい選択",
      "search_keys": [
        "会社員が取らない方がいい選択",
        "会社員ガ取ラナイ方ガイイ選択",
        "金持チガヤラナイコト / 会社員ガ取ラナイ方ガイイ選択",
        "金持ちがやらないこと / 会社員が取らない方がいい選択",
        "金持ちがやらないこと",
        "金持チガヤラナイコト"
      ],
      "near_candidates": []
    },
    {
      "guest_name": "就活",
      "search_keys": [
        "就活"
      ],
      "near_candidates": []
    },
    {
      "guest_name": "年収1000万円",
      "search_keys": [
        "年収1000万円"
      ],
      "near_candidates": []
    },
    {
      "guest_name": "副業がバレる理由",
      "search_keys": [
        "副業がばれる理由",
        "副業がバレる理由",
        "副業ガバレル理由"
      ],
      "near_candidates": []
    }
  ]
}